<RESULTS>
	<CODE>EXP1460802132</CODE>
	<TEXT>rand2</TEXT>
	<ALGO>
		<NAME>BSDM</NAME>
		<DATA>
			<SEARCH>8.18</SEARCH>
		</DATA>
		<DATA>
			<SEARCH>6.93</SEARCH>
		</DATA>
		<DATA>
			<SEARCH>6.93</SEARCH>
		</DATA>
		<DATA>
			<SEARCH>6.49</SEARCH>
		</DATA>
		<DATA>
			<SEARCH>6.68</SEARCH>
		</DATA>
		<DATA>
			<SEARCH>7.02</SEARCH>
		</DATA>
		<DATA>
			<SEARCH>6.91</SEARCH>
		</DATA>
		<DATA>
			<SEARCH>6.57</SEARCH>
		</DATA>
		<DATA>
			<SEARCH>6.75</SEARCH>
		</DATA>
		<DATA>
			<SEARCH>6.61</SEARCH>
		</DATA>
		<DATA>
			<SEARCH>6.90</SEARCH>
		</DATA>
		<DATA>
			<SEARCH>6.96</SEARCH>
		</DATA>
		<DATA>-</DATA>
		<DATA>
			<SEARCH>0.00</SEARCH>
		</DATA>
		<DATA>-</DATA>
		<DATA>
			<SEARCH>0.00</SEARCH>
		</DATA>
		<DATA>-</DATA>
		<DATA>
			<SEARCH>0.00</SEARCH>
		</DATA>
		<DATA>-</DATA>
		<DATA>
			<SEARCH>0.00</SEARCH>
		</DATA>
		<DATA>-</DATA>
		<DATA>
			<SEARCH>0.00</SEARCH>
		</DATA>
	</ALGO>
	<ALGO>
		<NAME>BSDM4</NAME>
		<DATA>-</DATA>
		<DATA>
			<SEARCH>0.00</SEARCH>
		</DATA>
		<DATA>
			<SEARCH>2.85</SEARCH>
		</DATA>
		<DATA>
			<SEARCH>2.29</SEARCH>
		</DATA>
		<DATA>
			<SEARCH>1.89</SEARCH>
		</DATA>
		<DATA>
			<SEARCH>1.77</SEARCH>
		</DATA>
		<DATA>
			<SEARCH>1.62</SEARCH>
		</DATA>
		<DATA>
			<SEARCH>1.38</SEARCH>
		</DATA>
		<DATA>
			<SEARCH>1.46</SEARCH>
		</DATA>
		<DATA>
			<SEARCH>1.45</SEARCH>
		</DATA>
		<DATA>
			<SEARCH>1.41</SEARCH>
		</DATA>
		<DATA>
			<SEARCH>1.45</SEARCH>
		</DATA>
		<DATA>
			<SEARCH>1.52</SEARCH>
		</DATA>
		<DATA>-</DATA>
		<DATA>
			<SEARCH>0.00</SEARCH>
		</DATA>
		<DATA>-</DATA>
		<DATA>
			<SEARCH>0.00</SEARCH>
		</DATA>
		<DATA>-</DATA>
		<DATA>
			<SEARCH>0.00</SEARCH>
		</DATA>
		<DATA>-</DATA>
		<DATA>
			<SEARCH>0.00</SEARCH>
		</DATA>
		<DATA>-</DATA>
		<DATA>
			<SEARCH>0.00</SEARCH>
		</DATA>
	</ALGO>
	<ALGO>
		<NAME>KBNDM</NAME>
		<DATA>
			<SEARCH>5.86</SEARCH>
		</DATA>
		<DATA>
			<SEARCH>4.79</SEARCH>
		</DATA>
		<DATA>
			<SEARCH>3.04</SEARCH>
		</DATA>
		<DATA>
			<SEARCH>1.83</SEARCH>
		</DATA>
		<DATA>
			<SEARCH>1.14</SEARCH>
		</DATA>
		<DATA>
			<SEARCH>0.92</SEARCH>
		</DATA>
		<DATA>
			<SEARCH>0.95</SEARCH>
		</DATA>
		<DATA>
			<SEARCH>0.86</SEARCH>
		</DATA>
		<DATA>
			<SEARCH>0.78</SEARCH>
		</DATA>
		<DATA>
			<SEARCH>0.93</SEARCH>
		</DATA>
		<DATA>
			<SEARCH>0.85</SEARCH>
		</DATA>
		<DATA>
			<SEARCH>0.92</SEARCH>
		</DATA>
		<DATA>-</DATA>
		<DATA>
			<SEARCH>0.00</SEARCH>
		</DATA>
		<DATA>-</DATA>
		<DATA>
			<SEARCH>0.00</SEARCH>
		</DATA>
		<DATA>-</DATA>
		<DATA>
			<SEARCH>0.00</SEARCH>
		</DATA>
		<DATA>-</DATA>
		<DATA>
			<SEARCH>0.00</SEARCH>
		</DATA>
		<DATA>-</DATA>
		<DATA>
			<SEARCH>0.00</SEARCH>
		</DATA>
	</ALGO>
	<ALGO>
		<NAME>NEW2</NAME>
		<DATA>-</DATA>
		<DATA>
			<SEARCH>0.00</SEARCH>
		</DATA>
		<DATA>
			<SEARCH>4.32</SEARCH>
		</DATA>
		<DATA>
			<SEARCH>2.66</SEARCH>
		</DATA>
		<DATA>
			<SEARCH>1.67</SEARCH>
		</DATA>
		<DATA>
			<SEARCH>1.07</SEARCH>
		</DATA>
		<DATA>
			<SEARCH>0.70</SEARCH>
		</DATA>
		<DATA>-</DATA>
		<DATA>
			<SEARCH>0.00</SEARCH>
		</DATA>
		<DATA>-</DATA>
		<DATA>
			<SEARCH>0.00</SEARCH>
		</DATA>
		<DATA>
			<SEARCH>0.64</SEARCH>
		</DATA>
		<DATA>
			<SEARCH>0.71</SEARCH>
		</DATA>
		<DATA>
			<SEARCH>0.59</SEARCH>
		</DATA>
		<DATA>
			<SEARCH>0.70</SEARCH>
		</DATA>
		<DATA>-</DATA>
		<DATA>
			<SEARCH>0.00</SEARCH>
		</DATA>
		<DATA>-</DATA>
		<DATA>
			<SEARCH>0.00</SEARCH>
		</DATA>
		<DATA>-</DATA>
		<DATA>
			<SEARCH>0.00</SEARCH>
		</DATA>
		<DATA>-</DATA>
		<DATA>
			<SEARCH>0.00</SEARCH>
		</DATA>
		<DATA>-</DATA>
		<DATA>
			<SEARCH>0.00</SEARCH>
		</DATA>
	</ALGO>
	<ALGO>
		<NAME>WOM</NAME>
		<DATA>
			<SEARCH>4.74</SEARCH>
		</DATA>
		<DATA>
			<SEARCH>5.76</SEARCH>
		</DATA>
		<DATA>
			<SEARCH>4.14</SEARCH>
		</DATA>
		<DATA>
			<SEARCH>4.50</SEARCH>
		</DATA>
		<DATA>
			<SEARCH>3.92</SEARCH>
		</DATA>
		<DATA>
			<SEARCH>3.56</SEARCH>
		</DATA>
		<DATA>
			<SEARCH>2.93</SEARCH>
		</DATA>
		<DATA>
			<SEARCH>2.65</SEARCH>
		</DATA>
		<DATA>
			<SEARCH>2.38</SEARCH>
		</DATA>
		<DATA>
			<SEARCH>2.24</SEARCH>
		</DATA>
		<DATA>
			<SEARCH>2.16</SEARCH>
		</DATA>
		<DATA>
			<SEARCH>1.92</SEARCH>
		</DATA>
		<DATA>-</DATA>
		<DATA>
			<SEARCH>0.00</SEARCH>
		</DATA>
		<DATA>-</DATA>
		<DATA>
			<SEARCH>0.00</SEARCH>
		</DATA>
		<DATA>-</DATA>
		<DATA>
			<SEARCH>0.00</SEARCH>
		</DATA>
		<DATA>-</DATA>
		<DATA>
			<SEARCH>0.00</SEARCH>
		</DATA>
		<DATA>-</DATA>
		<DATA>
			<SEARCH>0.00</SEARCH>
		</DATA>
	</ALGO>
	<BEST>
		<DATA>4.74</DATA>
		<DATA>2.85</DATA>
		<DATA>2.29</DATA>
		<DATA>1.67</DATA>
		<DATA>1.07</DATA>
		<DATA>0.70</DATA>
		<DATA>0.95</DATA>
		<DATA>0.86</DATA>
		<DATA>0.64</DATA>
		<DATA>0.71</DATA>
		<DATA>0.59</DATA>
		<DATA>0.70</DATA>
		<DATA>999999.00</DATA>
		<DATA>999999.00</DATA>
		<DATA>999999.00</DATA>
		<DATA>999999.00</DATA>
		<DATA>999999.00</DATA>
	</BEST>
</RESULTS>